datasette_sqlite_graft/__init__.py
datasette_sqlite_graft-0.2.1.dist-info/METADATA
datasette_sqlite_graft-0.2.1.dist-info/WHEEL
datasette_sqlite_graft-0.2.1.dist-info/entry_points.txt
datasette_sqlite_graft-0.2.1.dist-info/top_level.txt
datasette_sqlite_graft-0.2.1.dist-info/RECORD
