Metadata-Version: 2.1
Name: datasette-sqlite-graft
Version: 0.2.1
Home-page: https://github.com/orbitinghail/graft
Author: Carl Sverre
License: MIT OR Apache
Requires-Dist: datasette
Requires-Dist: sqlite-graft (==0.2.1)
